exhbma/__init__.py
exhbma/constant_regression.py
exhbma/exhaustive_search.py
exhbma/integrate.py
exhbma/linear_regression.py
exhbma/plot.py
exhbma/probabilities.py
exhbma/scaler.py
exhbma-0.1.12.dist-info/WHEEL
exhbma-0.1.12.dist-info/METADATA
exhbma-0.1.12.dist-info/RECORD
